primenumbers_sergio/__init__.py
primenumbers_sergio-1.0.dist-info/LICENSE
primenumbers_sergio-1.0.dist-info/METADATA
primenumbers_sergio-1.0.dist-info/WHEEL
primenumbers_sergio-1.0.dist-info/top_level.txt
primenumbers_sergio-1.0.dist-info/RECORD
