Metadata-Version: 2.1
Name: primenumbers-sergio
Version: 1.0
Summary: A tool to calc prime numbers.
Home-page: UNKNOWN
Author: Sergio Arcila
Author-email: sergioarcila1998@hotmail.com
License: GNU GPLv3
Keywords: pyoperaciones mathematical operations
Platform: UNKNOWN
Classifier: Development Status :: 4 - Beta
Classifier: Intended Audience :: Developers
Classifier: Topic :: Utilities
Classifier: License :: OSI Approved :: GNU General Public License v3 (GPLv3)
Classifier: Programming Language :: Python :: 3
Classifier: Operating System :: OS Independent
